thoth/storages/__init__.py
thoth/storages/advisers.py
thoth/storages/advisers_cache.py
thoth/storages/analyses.py
thoth/storages/analyses_by_digest.py
thoth/storages/analyses_cache.py
thoth/storages/base.py
thoth/storages/buildlogs.py
thoth/storages/buildlogs_analyses_cache.py
thoth/storages/buildlogs_parsed.py
thoth/storages/ceph.py
thoth/storages/ceph_cache.py
thoth/storages/cli.py
thoth/storages/dependency_monkey_reports.py
thoth/storages/dependency_monkey_requests.py
thoth/storages/exceptions.py
thoth/storages/graph_backup.py
thoth/storages/inspections.py
thoth/storages/logs.py
thoth/storages/observations.py
thoth/storages/provenance.py
thoth/storages/provenance_cache.py
thoth/storages/py.typed
thoth/storages/result_base.py
thoth/storages/result_schema.py
thoth/storages/revsolvers.py
thoth/storages/security_indicators.py
thoth/storages/solvers.py
thoth/storages/sync.py
thoth/storages/data/alembic.ini
thoth/storages/data/alembic/env.py
thoth/storages/data/alembic/script.py.mako
thoth/storages/data/alembic/versions/0165f03250a6_add_cve_timestamp_table.py
thoth/storages/data/alembic/versions/079e1d92f9d4_add_is_external_to_packageextractrun.py
thoth/storages/data/alembic/versions/081bee0d9587_create_index_for_thoth_s2i_specific_.py
thoth/storages/data/alembic/versions/0c8eab5d4197_add_indexes_for_abi_compatability_.py
thoth/storages/data/alembic/versions/0ea53ec16d6b_use_text_instead_of_strings_all_over_.py
thoth/storages/data/alembic/versions/10925df620b1_add_datetime_for_filtering_to_.py
thoth/storages/data/alembic/versions/125a71b49a50_add_parameters_to_deal_with_unsolved_.py
thoth/storages/data/alembic/versions/184e698fe2c2_artifact_should_link_just_to_entity.py
thoth/storages/data/alembic/versions/1a8150ac45e0_delete_to_refactor_schema_for_python_.py
thoth/storages/data/alembic/versions/1ee67d9a7861_enable_nullable_limit_latest_versions.py
thoth/storages/data/alembic/versions/1fbd52a03c73_adjust_types_for_conv_pi.py
thoth_storages-0.74.2.dist-info/LICENSE
thoth_storages-0.74.2.dist-info/METADATA
thoth_storages-0.74.2.dist-info/WHEEL
thoth_storages-0.74.2.dist-info/entry_points.txt
thoth_storages-0.74.2.dist-info/top_level.txt
thoth_storages-0.74.2.dist-info/RECORD
