Metadata-Version: 2.1
Name: thoth-storages
Version: 0.74.2
Summary: Storage and database adapters available in project Thoth
Home-page: https://github.com/thoth-station/storages
Author: Fridolin Pokorny
Author-email: fridolin@redhat.com
Maintainer: Francesco Murdaca
Maintainer-email: fmurdaca@redhat.com
License: GPLv3+
Platform: UNKNOWN
License-File: LICENSE
Requires-Dist: alembic
Requires-Dist: boto3
Requires-Dist: click
Requires-Dist: packaging
Requires-Dist: psycopg2-binary
Requires-Dist: python-dateutil
Requires-Dist: pyyaml
Requires-Dist: sqlalchemy-utils
Requires-Dist: sqlalchemy (<1.4.0)
Requires-Dist: thoth-common
Requires-Dist: thoth-license-solver (>=0.1.4)
Requires-Dist: thoth-python
Requires-Dist: voluptuous
